Metadata-Version: 2.1
Name: validatejson
Version: 0.2
Summary: Simplistic tool to validate JSON payload against JSON schema
Home-page: https://github.com/deepakcpakhale06/validatejson
Author: deeppy
License: UNKNOWN
Download-URL: https://github.com/deepakcpakhale06/validatejson/tree/main/dist/validatejson-0.1.tar
Platform: UNKNOWN
Classifier: Development Status :: 3 - Alpha
Classifier: Intended Audience :: Developers
Classifier: Topic :: Software Development :: Build Tools
Classifier: License :: OSI Approved :: MIT License
Classifier: Programming Language :: Python :: 3
